{"comments_disabled": false, "id": "1962208460334552667", "edge_media_to_caption": {"edges": [{"node": {"text": "\ud64d\ub300 \ucd5c\uace0\uc758 \ubc25\uc9d1 \uc220\uc9d1 \uc6b0\ub9ac\uc758 \uc0ac\ub791\uc9d1 <\ud574\ub2ec\ubc25\uc220>\n\ub9db\ub09c \uc694\ub9ac\uac00 \ub05d\ub3c4 \uc5c6\uc774 \ub098\uc640!!!\n\uc220 \uc74c\uccad \uba39\uc74c! \uc5b4\uc82f\ubc24\uc5d4 \ub9d0\ubc8c\uc8fc\uae4c\uc9c0.......\ud83d\ude0b\ud83d\ude0b\ud83d\ude0b\ud83d\udcaa\ud83d\udcaa\ud83d\udcaa"}}]}, "shortcode": "Bs7KjLNgdZb", "edge_media_to_comment": {"count": 2}, "taken_at_timestamp": 1548133498, "dimensions": {"height": 720, "width": 1080}, "display_url": "https://instagram.ficn2-1.fna.fbcdn.net/v/t51.2885-15/e35/49732960_222934161991197_3032005467192545544_n.jpg?_nc_ht=instagram.ficn2-1.fna.fbcdn.net&_nc_cat=109&_nc_ohc=BZGVxSJR_F0AX-eG3SA&oh=4b63b8b40ab0dd31948a1c7e667ab182&oe=5ED71BC7", "edge_liked_by": {"count": 63}, "edge_media_preview_like": {"count": 63}, "owner": {"id": "2802289693"}, "thumbnail_src": "https://instagram.ficn2-1.fna.fbcdn.net/v/t51.2885-15/sh0.08/e35/c180.0.720.720a/s640x640/49732960_222934161991197_3032005467192545544_n.jpg?_nc_ht=instagram.ficn2-1.fna.fbcdn.net&_nc_cat=109&_nc_ohc=BZGVxSJR_F0AX-eG3SA&oh=3523a9f266ebe29a21b83d0542e81502&oe=5E9DADF3", "thumbnail_resources": [{"src": "https://instagram.ficn2-1.fna.fbcdn.net/v/t51.2885-15/e35/c180.0.720.720a/s150x150/49732960_222934161991197_3032005467192545544_n.jpg?_nc_ht=instagram.ficn2-1.fna.fbcdn.net&_nc_cat=109&_nc_ohc=BZGVxSJR_F0AX-eG3SA&oh=7c660ff1e70b0cf4e1bf4c8b51bd9fad&oe=5ED7DF9B", "config_width": 150, "config_height": 150}, {"src": "https://instagram.ficn2-1.fna.fbcdn.net/v/t51.2885-15/e35/c180.0.720.720a/s240x240/49732960_222934161991197_3032005467192545544_n.jpg?_nc_ht=instagram.ficn2-1.fna.fbcdn.net&_nc_cat=109&_nc_ohc=BZGVxSJR_F0AX-eG3SA&oh=566842ad7f1236b6dac74c0fddf0d020&oe=5EA49DD1", "config_width": 240, "config_height": 240}, {"src": "https://instagram.ficn2-1.fna.fbcdn.net/v/t51.2885-15/e35/c180.0.720.720a/s320x320/49732960_222934161991197_3032005467192545544_n.jpg?_nc_ht=instagram.ficn2-1.fna.fbcdn.net&_nc_cat=109&_nc_ohc=BZGVxSJR_F0AX-eG3SA&oh=a872c52b334786b538e896ed3d56643e&oe=5E9F3B6B", "config_width": 320, "config_height": 320}, {"src": "https://instagram.ficn2-1.fna.fbcdn.net/v/t51.2885-15/e35/c180.0.720.720a/s480x480/49732960_222934161991197_3032005467192545544_n.jpg?_nc_ht=instagram.ficn2-1.fna.fbcdn.net&_nc_cat=109&_nc_ohc=BZGVxSJR_F0AX-eG3SA&oh=99b0000e1d9a54ab2ac5172c7b4ca9c3&oe=5E94E231", "config_width": 480, "config_height": 480}, {"src": "https://instagram.ficn2-1.fna.fbcdn.net/v/t51.2885-15/sh0.08/e35/c180.0.720.720a/s640x640/49732960_222934161991197_3032005467192545544_n.jpg?_nc_ht=instagram.ficn2-1.fna.fbcdn.net&_nc_cat=109&_nc_ohc=BZGVxSJR_F0AX-eG3SA&oh=3523a9f266ebe29a21b83d0542e81502&oe=5E9DADF3", "config_width": 640, "config_height": 640}], "is_video": false, "tags": [], "urls": ["https://instagram.ficn2-1.fna.fbcdn.net/v/t51.2885-15/e35/49732960_222934161991197_3032005467192545544_n.jpg?_nc_ht=instagram.ficn2-1.fna.fbcdn.net&_nc_cat=109&_nc_ohc=BZGVxSJR_F0AX-eG3SA&oh=4b63b8b40ab0dd31948a1c7e667ab182&oe=5ED71BC7", "https://instagram.ficn2-1.fna.fbcdn.net/v/t51.2885-15/e35/49858433_2265814203684024_395846482324540464_n.jpg?_nc_ht=instagram.ficn2-1.fna.fbcdn.net&_nc_cat=100&_nc_ohc=Y-o5zrzdz8cAX8k9c6v&oh=690d6119f20c9a0926e497b1eb13b50a&oe=5E9DA0FD", "https://instagram.ficn2-1.fna.fbcdn.net/v/t51.2885-15/e35/49933799_620905651674017_127444135361904228_n.jpg?_nc_ht=instagram.ficn2-1.fna.fbcdn.net&_nc_cat=105&_nc_ohc=ZVL4EHoWCq0AX-B_4pw&oh=9bec19ca36cab144ad865502052acb51&oe=5E9FF612", "https://instagram.ficn2-1.fna.fbcdn.net/v/t51.2885-15/e35/49472601_420397798500919_5535882537523883422_n.jpg?_nc_ht=instagram.ficn2-1.fna.fbcdn.net&_nc_cat=107&_nc_ohc=G-d-4OZSXjEAX_iOnJj&oh=1dd6d59da43310a1f38f139204a00765&oe=5E9F965E", "https://instagram.ficn2-1.fna.fbcdn.net/v/t51.2885-15/e35/50643984_547105669140885_3570661280434740563_n.jpg?_nc_ht=instagram.ficn2-1.fna.fbcdn.net&_nc_cat=109&_nc_ohc=Q9g8EQZbO9sAX_CI_r0&oh=da761fac67fb88022ed436aa5af0df27&oe=5ED8F806"]}